{
  "minicraft.tutorial.start_getting_wood": {
    "index": 0,
    "description": "minicraft.tutorial.start_getting_wood.description",
    "criteria": {
      "has_wood": {
        "trigger": "inventory_changed",
        "conditions": {
          "items": [
            {
              "items": [
                "wood"
              ]
            }
          ]
        }
      }
    }
  },
  "minicraft.tutorial.getting_wood": {
    "index": 1,
    "description": "minicraft.tutorial.getting_wood.description",
    "criteria": {
      "has_wood": {
        "trigger": "inventory_changed",
        "conditions": {
          "items": [
            {
              "items": [
                "wood"
              ],
              "count": {
                "min": 10
              }
            }
          ]
        }
      }
    }
  },
  "minicraft.tutorial.getting_workbench": {
    "index": 2,
    "description": "minicraft.tutorial.getting_workbench.description",
    "criteria": {
      "has_workbench": {
        "trigger": "inventory_changed",
        "conditions": {
          "items": [
            {
              "items": [
                "workbench"
              ]
            }
          ]
        }
      }
    }
  },
  "minicraft.tutorial.getting_wooden_pickaxe": {
    "index": 3,
    "description": "minicraft.tutorial.getting_wooden_pickaxe.description",
    "criteria": {
      "has_wooden_pickaxe": {
        "trigger": "inventory_changed",
        "conditions": {
          "items": [
            {
              "items": [
                "wood pickaxe"
              ]
            }
          ]
        }
      }
    }
  },
  "minicraft.tutorial.getting_rocks": {
    "index": 4,
    "description": "minicraft.tutorial.getting_rocks.description",
    "criteria": {
      "has_rock": {
        "trigger": "inventory_changed",
        "conditions": {
          "items": [
            {
              "items": [
                "stone"
              ],
              "count": {
                "min": 5
              }
            }
          ]
        }
      },
      "has_coal": {
        "trigger": "inventory_changed",
        "conditions": {
          "items": [
            {
              "items": [
                "coal"
              ],
              "count": {
                "min": 5
              }
            }
          ]
        }
      }
    }
  }
}
